JUtils/AutoDoc.py
JUtils/JArr.py
JUtils/JColors.py
JUtils/JConst.py
JUtils/JConv.py
JUtils/JNum.py
JUtils/JOut.py
JUtils/JStr.py
JUtils/__init__.py
JUtils-3.0.4.dist-info/LICENSE
JUtils-3.0.4.dist-info/METADATA
JUtils-3.0.4.dist-info/WHEEL
JUtils-3.0.4.dist-info/top_level.txt
JUtils-3.0.4.dist-info/RECORD
