Metadata-Version: 2.1
Name: JUtils
Version: 3.0.4
Summary: Package containing various utility functions i needed now and then, that i wanted to share
Author-email: Jan Seifert <jan@seifert-online.de>
Project-URL: Homepage, https://github.com/Logogistiks/JUtils
Classifier: Programming Language :: Python :: 3
Classifier: License :: OSI Approved :: MIT License
Classifier: Operating System :: OS Independent
Requires-Python: >=3.7
License-File: LICENSE
